[
  {
    "category": "Trending in Turkey",
    "title": "turkey",
    "tweetCount": "125.6K Tweets"
  },
  {
    "category": "Trending in Turkey",
    "title": "web3",
    "tweetCount": "8.6433 Tweets"
  },
  {
    "category": "Trending in Turkey",
    "title": "Elon Musk",
    "tweetCount": "250.5K Tweets"
  },
  {
    "category": "Trending in Turkey",
    "title": "turkey",
    "tweetCount": "125.6K Tweets"
  },
  {
    "category": "Trending in Turkey",
    "title": "web3",
    "tweetCount": "8.6433 Tweets"
  },
  {
    "category": "Trending in Turkey",
    "title": "Elon Musk",
    "tweetCount": "250.5K Tweets"
  },
  {
    "category": "Trending in Turkey",
    "title": "turkey",
    "tweetCount": "125.6K Tweets"
  },
  {
    "category": "Trending in Turkey",
    "title": "web3",
    "tweetCount": "8.6433 Tweets"
  },
  {
    "category": "Trending in Turkey",
    "title": "Elon Musk",
    "tweetCount": "250.5K Tweets"
  }
]
